{"all_cpu_hours": 762404.0758, "num_uniq_job_ids": 422059, "pct_good_cpu_hours": 92.0865, "pct_rmed_jobs": 3.9284, "pct_short_jobs": 4.0478, "pct_jobs_with_more_than_1_exec_att": 7.9389, "pct_jobs_with_1+_holds": 1.0345, "pct_jobs_using_s'ty": 72.2525, "shadw_starts_per_job_id": 1.3052, "exec_atts_per_shadw_start": 0.8228, "holds_per_job_id": 0.0141, "min_hrs": 0.0167, "25pct_hrs": 0.3903, "med_hrs": 0.9397, "75pct_hrs": 2.5931, "95pct_hrs": 5.4114, "max_hrs": 175.7233, "mean_hrs": 1.8124, "std_hrs": 2.0906, "input_files_xferd_per_exec_att": 2.7332, "input_mb_xferd_per_exec_att": 10.4283, "input_mb_per_file": 4.201, "output_files_xferd_per_exec_att": 2.3644, "output_mb_xferd_per_exec_att": 3.3115, "output_mb_per_file": 1.5421, "max_rqst_mem_mb": 40960, "med_used_mem_mb": 1465, "max_used_mem_mb": 195313, "max_rqst_cpus": 8, "good_cpu_hours": 702070.8978, "cpu_hours_per_bad_exec_att": 1.0833, "num_exec_atts": 453283, "num_shadw_starts": 550875, "num_job_holds": 5930, "num_rmed_jobs": 16580, "num_dag_node_jobs": 120737, "num_jobs_with_more_than_1_exec_att": 33507, "num_jobs_with_1+_holds": 4366, "num_short_jobs": 17084, "num_local_univ_jobs": 1841, "num_sched_univ_jobs": 11, "num_s'ty_jobs": 304948, "num_schedds": 10, "date": "2021-12-09", "query": "OSG-schedd-job-history", "report_period": "daily", "num_projects": 29, "num_users": 34, "num_sites": 60}