{"all_cpu_hours": 485041.6208, "num_uniq_job_ids": 397605, "pct_good_cpu_hours": 87.4296, "pct_rmed_jobs": 2.8571, "pct_short_jobs": 6.9481, "pct_jobs_with_more_than_1_exec_att": 7.6196, "pct_jobs_with_1+_holds": 4.3505, "shadw_starts_per_job_id": 1.3317, "exec_atts_per_shadw_start": 0.8917, "holds_per_job_id": 0.1778, "min_hrs": 0.0167, "25pct_hrs": 0.4994, "med_hrs": 0.6956, "75pct_hrs": 1.5061, "95pct_hrs": 2.9297, "max_hrs": 64.4875, "mean_hrs": 1.1036, "std_hrs": 1.2481, "avg_mb_sent": 4.2374, "max_mb_sent": 1270.08, "avg_mb_recv": 257.5414, "max_mb_recv": 3459.6682, "max_rqst_mem_mb": 28000, "med_used_mem_mb": 733, "max_used_mem_mb": 122071, "max_rqst_cpus": 8, "good_cpu_hours": 424069.8797, "cpu_hours_per_bad_exec_att": 0.566, "num_exec_atts": 472131, "num_shadw_starts": 529487, "num_job_holds": 70679, "num_rmed_jobs": 11360, "num_dag_node_jobs": 136683, "num_jobs_with_more_than_1_exec_att": 30296, "num_jobs_with_1+_holds": 17298, "num_short_jobs": 27626, "num_local_univ_jobs": 373, "num_sched_univ_jobs": 14, "num_schedds": 8, "date": "2021-08-23", "query": "OSG-schedd-job-history", "report_period": "daily", "num_projects": 28, "num_users": 32, "num_sites": 53}