{"all_cpu_hours": 562906.7622, "num_uniq_job_ids": 738794, "pct_good_cpu_hours": 87.7678, "pct_rmed_jobs": 1.6697, "pct_short_jobs": 3.8873, "pct_jobs_with_more_than_1_exec_att": 42.2979, "pct_jobs_with_1+_holds": 44.3486, "shadw_starts_per_job_id": 2.1983, "exec_atts_per_shadw_start": 0.9727, "holds_per_job_id": 1.2114, "min_hrs": 0.0167, "25pct_hrs": 0.2394, "med_hrs": 0.3111, "75pct_hrs": 0.7444, "95pct_hrs": 1.7675, "max_hrs": 42.6617, "mean_hrs": 0.684, "std_hrs": 1.2113, "avg_mb_sent": 1.9348, "max_mb_sent": 344.3716, "avg_mb_recv": 21.7661, "max_mb_recv": 1742.0072, "max_rqst_mem_mb": 81920, "med_used_mem_mb": 733.0, "max_used_mem_mb": 195313, "max_rqst_cpus": 8, "good_cpu_hours": 494050.99, "cpu_hours_per_bad_exec_att": 0.0246, "num_exec_atts": 1579683, "num_shadw_starts": 1624087, "num_job_holds": 894961, "num_rmed_jobs": 12336, "num_dag_node_jobs": 106405, "num_jobs_with_more_than_1_exec_att": 312494, "num_jobs_with_1+_holds": 327645, "num_short_jobs": 28719, "num_local_univ_jobs": 0, "num_sched_univ_jobs": 0, "num_schedds": 8, "date": "2021-09-20", "query": "OSG-schedd-job-history", "report_period": "daily", "num_projects": 24, "num_users": 29, "num_sites": 51}