{"all_cpu_hours": 574510.8158, "num_uniq_job_ids": 406131, "pct_good_cpu_hours": 85.8988, "pct_rmed_jobs": 1.7583, "pct_short_jobs": 37.482, "pct_jobs_with_more_than_1_exec_att": 8.2136, "pct_jobs_with_1+_holds": 2.8752, "shadw_starts_per_job_id": 1.249, "exec_atts_per_shadw_start": 0.9111, "holds_per_job_id": 0.0584, "min_hrs": 0.0167, "25pct_hrs": 0.3761, "med_hrs": 0.9514, "75pct_hrs": 1.9197, "95pct_hrs": 6.9781, "max_hrs": 46.4878, "mean_hrs": 1.8079, "std_hrs": 2.3671, "avg_mb_sent": 19.3746, "max_mb_sent": 13548.0064, "avg_mb_recv": 32.7361, "max_mb_recv": 10736.8069, "max_rqst_mem_mb": 51200, "med_used_mem_mb": 733, "max_used_mem_mb": 36622, "max_rqst_cpus": 8, "good_cpu_hours": 493497.65, "cpu_hours_per_bad_exec_att": 1.3779, "num_exec_atts": 462139, "num_shadw_starts": 507259, "num_job_holds": 23733, "num_rmed_jobs": 7141, "num_dag_node_jobs": 172167, "num_jobs_with_more_than_1_exec_att": 33358, "num_jobs_with_1+_holds": 11677, "num_short_jobs": 152226, "num_local_univ_jobs": 302, "num_sched_univ_jobs": 33, "num_schedds": 11, "date": "2021-08-31", "query": "OSG-schedd-job-history", "report_period": "daily", "num_projects": 33, "num_users": 41, "num_sites": 53}