{"all_cpu_hours": 977570.4444, "num_uniq_job_ids": 258749, "pct_good_cpu_hours": 57.3752, "pct_rmed_jobs": 19.3346, "pct_short_jobs": 4.8781, "pct_jobs_with_more_than_1_exec_att": 5.0555, "pct_jobs_with_1+_holds": 4.7934, "pct_jobs_using_s'ty": 33.1758, "shadw_starts_per_job_id": 1.061, "exec_atts_per_shadw_start": 0.9489, "holds_per_job_id": 0.0567, "min_hrs": 0.0167, "25pct_hrs": 0.625, "med_hrs": 1.8347, "75pct_hrs": 3.1203, "95pct_hrs": 6.035, "max_hrs": 46.4478, "mean_hrs": 2.6341, "std_hrs": 4.3602, "input_files_xferd_per_exec_att": 14.5759, "input_mb_xferd_per_exec_att": 42.3852, "input_mb_per_file": 2.9079, "output_files_xferd_per_exec_att": 4.1348, "output_mb_xferd_per_exec_att": 15.1355, "output_mb_per_file": 3.6605, "max_rqst_mem_mb": 40000, "med_used_mem_mb": 733.0, "max_used_mem_mb": 146485, "max_rqst_cpus": 25, "good_cpu_hours": 560882.8328, "cpu_hours_per_bad_exec_att": 8.0062, "num_exec_atts": 260497, "num_shadw_starts": 274524, "num_job_holds": 14684, "num_rmed_jobs": 50028, "num_dag_node_jobs": 140810, "num_jobs_with_more_than_1_exec_att": 13081, "num_jobs_with_1+_holds": 12403, "num_short_jobs": 12622, "num_local_univ_jobs": 4274, "num_sched_univ_jobs": 21, "num_s'ty_jobs": 85842, "num_schedds": 8, "date": "2021-10-06", "query": "OSG-schedd-job-history", "report_period": "daily", "num_projects": 29, "num_users": 44, "num_sites": 57}