{"all_cpu_hours": 140760.6619, "num_uniq_job_ids": 80021, "pct_good_cpu_hours": 50.3152, "pct_rmed_jobs": 8.3316, "pct_short_jobs": 9.6112, "pct_jobs_with_more_than_1_exec_att": 9.5787, "pct_jobs_with_1+_holds": 11.8506, "shadw_starts_per_job_id": 2.2007, "exec_atts_per_shadw_start": 0.5153, "holds_per_job_id": 1.0331, "min_hrs": 0.0167, "25pct_hrs": 0.3028, "med_hrs": 0.5578, "75pct_hrs": 0.9231, "95pct_hrs": 2.8067, "max_hrs": 132.2086, "mean_hrs": 0.9349, "std_hrs": 3.1556, "avg_mb_sent": 8.153, "max_mb_sent": 39827.9844, "avg_mb_recv": 26.9291, "max_mb_recv": 3695.328, "max_rqst_mem_mb": 28000, "med_used_mem_mb": 733, "max_used_mem_mb": 73243, "max_rqst_cpus": 10, "good_cpu_hours": 70823.9686, "cpu_hours_per_bad_exec_att": 4.1816, "num_exec_atts": 90747, "num_shadw_starts": 176102, "num_job_holds": 82672, "num_rmed_jobs": 6667, "num_dag_node_jobs": 34924, "num_jobs_with_more_than_1_exec_att": 7665, "num_jobs_with_1+_holds": 9483, "num_short_jobs": 7691, "num_local_univ_jobs": 130, "num_sched_univ_jobs": 13, "num_schedds": 9, "date": "2021-08-16", "query": "OSG-schedd-job-history", "report_period": "daily", "num_projects": 32, "num_users": 36, "num_sites": 48}