{"all_cpu_hours": 601598.93, "num_uniq_job_ids": 278264, "pct_good_cpu_hours": 64.306, "pct_ckpt_able": 4.504, "pct_rmed_jobs": 12.6121, "pct_short_jobs": 16.2037, "pct_jobs_with_more_than_1_exec_att": 5.8171, "pct_jobs_with_1+_holds": 6.4877, "pct_jobs_over_rqst_disk": 0.6311, "pct_jobs_using_s'ty": 52.0966, "total_files_xferd": 14208188, "shadw_starts_per_job_id": 1.1744, "exec_atts_per_shadw_start": 0.8914, "holds_per_job_id": 0.1126, "mean_actv_hrs": 1.4441, "mean_setup_secs": 15.4957, "min_hrs": 0.0167, "25pct_hrs": 0.1422, "med_hrs": 0.5708, "75pct_hrs": 1.4439, "95pct_hrs": 7.5372, "max_hrs": 53.3072, "mean_hrs": 1.6005, "std_hrs": 3.015, "input_files_per_exec_att": 55.1012, "output_files_per_job": 3.9701, "max_rqst_mem_mb": 101376, "med_used_mem_mb": 74.0, "max_used_mem_mb": 97657, "max_rqst_disk_gb": 157.2864, "max_used_disk_gb": 32.5, "max_rqst_cpus": 16, "good_cpu_hours": 386863.97, "cpu_hours_per_bad_exec_att": 5.8467, "num_exec_atts": 291290, "num_shadw_starts": 326788, "num_job_holds": 31344, "num_rmed_jobs": 35095, "num_dag_node_jobs": 95267, "num_jobs_with_more_than_1_exec_att": 16187, "num_jobs_with_1+_holds": 18053, "num_jobs_over_rqst_disk": 1756, "num_short_jobs": 45089, "num_local_univ_jobs": 180, "num_sched_univ_jobs": 62, "num_ckpt_able_jobs": 12533, "num_s'ty_jobs": 144966, "num_schedds": 10, "date": "2022-08-16", "query": "OSG-schedd-job-history", "report_period": "daily", "num_projects": 39, "num_users": 47, "num_sites": 41}