{"all_cpu_hours": 139178.8406, "num_uniq_job_ids": 103245, "pct_good_cpu_hours": 64.1031, "pct_rmed_jobs": 28.7617, "pct_short_jobs": 13.4283, "pct_jobs_with_more_than_1_exec_att": 8.874, "pct_jobs_with_1+_holds": 2.7101, "pct_jobs_using_s'ty": 30.2572, "shadw_starts_per_job_id": 0.9621, "exec_atts_per_shadw_start": 0.8709, "holds_per_job_id": 0.0547, "mean_actv_hrs": 1.3893, "mean_setup_secs": 19.7051, "min_hrs": 0.0167, "25pct_hrs": 0.1792, "med_hrs": 0.6357, "75pct_hrs": 1.6439, "95pct_hrs": 5.7297, "max_hrs": 39.3933, "mean_hrs": 1.4339, "std_hrs": 2.2327, "input_files_xferd_per_exec_att": 47.661, "input_mb_xferd_per_exec_att": 2.245, "input_mb_per_file": 0.0836, "output_files_xferd_per_exec_att": 1.9615, "output_mb_xferd_per_exec_att": 60.3089, "output_mb_per_file": 54.5768, "max_rqst_mem_mb": 48000, "med_used_mem_mb": 196.0, "max_used_mem_mb": 17090, "max_rqst_cpus": 4, "good_cpu_hours": 89217.9992, "cpu_hours_per_bad_exec_att": 4.06, "num_exec_atts": 86511, "num_shadw_starts": 99333, "num_job_holds": 5650, "num_rmed_jobs": 29695, "num_dag_node_jobs": 22291, "num_jobs_with_more_than_1_exec_att": 9162, "num_jobs_with_1+_holds": 2798, "num_short_jobs": 13864, "num_local_univ_jobs": 1093, "num_sched_univ_jobs": 8, "num_s'ty_jobs": 31239, "num_schedds": 10, "date": "2022-01-19", "query": "OSG-schedd-job-history", "report_period": "daily", "num_projects": 27, "num_users": 33, "num_sites": 54}