{"all_cpu_hours": 321054.6417, "num_uniq_job_ids": 480371, "pct_good_cpu_hours": 74.9549, "pct_rmed_jobs": 2.6427, "pct_short_jobs": 1.5147, "pct_jobs_with_more_than_1_exec_att": 2.5695, "pct_jobs_with_1+_holds": 1.4366, "pct_jobs_using_s'ty": 39.8286, "total_files_xferd": 3229011, "shadw_starts_per_job_id": 1.0407, "exec_atts_per_shadw_start": 0.9738, "holds_per_job_id": 0.0233, "mean_actv_hrs": -3669417014.0124, "mean_setup_secs": -13209901252062.887, "min_hrs": 0.0167, "25pct_hrs": 0.0506, "med_hrs": 0.1133, "75pct_hrs": 0.165, "95pct_hrs": 2.8147, "max_hrs": 134.5522, "mean_hrs": 0.4993, "std_hrs": 1.5943, "input_files_per_exec_att": 4.0876, "output_files_per_job": 2.6981, "max_rqst_mem_mb": 102400, "med_used_mem_mb": 74, "max_used_mem_mb": 73243, "max_rqst_cpus": 8, "good_cpu_hours": 240646.295, "cpu_hours_per_bad_exec_att": 3.7406, "num_exec_atts": 486839, "num_shadw_starts": 499945, "num_job_holds": 11184, "num_rmed_jobs": 12695, "num_dag_node_jobs": 183905, "num_jobs_with_more_than_1_exec_att": 12343, "num_jobs_with_1+_holds": 6901, "num_short_jobs": 7276, "num_local_univ_jobs": 50, "num_sched_univ_jobs": 360, "num_s'ty_jobs": 191325, "num_schedds": 10, "date": "2022-06-01", "query": "OSG-schedd-job-history", "report_period": "daily", "num_projects": 29, "num_users": 38, "num_sites": 32}