{"all_cpu_hours": 1298815.7808, "num_uniq_job_ids": 325006, "pct_good_cpu_hours": 89.3002, "pct_ckpt_able": 2.7947, "pct_rmed_jobs": 0.8163, "pct_short_jobs": 14.8046, "pct_jobs_with_more_than_1_exec_att": 2.8132, "pct_jobs_with_1+_holds": 3.7104, "pct_jobs_over_rqst_disk": 0.0471, "pct_jobs_using_s'ty": 74.0749, "total_files_xferd": 1517328, "shadw_starts_per_job_id": 1.1907, "exec_atts_per_shadw_start": 0.8392, "holds_per_job_id": 0.0667, "mean_actv_hrs": 2.8768, "mean_setup_secs": 28.4212, "min_hrs": 0.0167, "25pct_hrs": 1.2342, "med_hrs": 2.9, "75pct_hrs": 5.0133, "95pct_hrs": 11.035, "max_hrs": 74.7656, "mean_hrs": 3.784, "std_hrs": 4.2386, "input_files_per_exec_att": 3.0204, "output_files_per_job": 3.0923, "max_rqst_mem_mb": 131072, "med_used_mem_mb": 196, "max_used_mem_mb": 73243, "max_rqst_disk_gb": 157.2864, "max_used_disk_gb": 25.0, "max_rqst_cpus": 16, "good_cpu_hours": 1159845.1072, "cpu_hours_per_bad_exec_att": 9.9232, "num_exec_atts": 324750, "num_shadw_starts": 386982, "num_job_holds": 21665, "num_rmed_jobs": 2653, "num_dag_node_jobs": 160843, "num_jobs_with_more_than_1_exec_att": 9143, "num_jobs_with_1+_holds": 12059, "num_jobs_over_rqst_disk": 153, "num_short_jobs": 48116, "num_local_univ_jobs": 10603, "num_sched_univ_jobs": 37, "num_ckpt_able_jobs": 9083, "num_s'ty_jobs": 240748, "num_schedds": 9, "date": "2022-12-27", "query": "OSG-schedd-job-history", "report_period": "daily", "num_projects": 29, "num_users": 33, "num_sites": 48}