{"all_cpu_hours": 958782.5081, "num_uniq_job_ids": 560388, "pct_good_cpu_hours": 78.0924, "pct_ckpt_able": 26.4058, "pct_rmed_jobs": 4.1077, "pct_short_jobs": 22.2533, "pct_jobs_with_more_than_1_exec_att": 3.9714, "pct_jobs_with_1+_holds": 6.278, "pct_jobs_over_rqst_disk": 2.8983, "pct_jobs_using_s'ty": 51.1171, "total_files_xferd": 3479275, "osdf_files_xferd": 415571, "pct_osdf_files": 11.9442, "pct_osdf_bytes": 71.1574, "shadw_starts_per_job_id": 1.2724, "exec_atts_per_shadw_start": 0.8169, "holds_per_job_id": 0.1618, "mean_actv_hrs": 1.2382, "mean_setup_secs": 70.8557, "min_hrs": 0.0167, "25pct_hrs": 0.3789, "med_hrs": 0.6675, "75pct_hrs": 1.5778, "95pct_hrs": 6.4528, "max_hrs": 39.3975, "mean_hrs": 1.5224, "std_hrs": 2.409, "input_files_per_exec_att": 3.8768, "output_files_per_job": 2.5513, "max_rqst_mem_mb": 160000, "med_used_mem_mb": 98, "max_used_mem_mb": 122071, "max_rqst_disk_gb": 31.4573, "max_used_disk_gb": 225.0, "max_rqst_cpus": 4, "good_cpu_hours": 748735.8817, "cpu_hours_per_bad_exec_att": 3.4132, "num_exec_atts": 582462, "num_shadw_starts": 713010, "num_job_holds": 90691, "num_rmed_jobs": 23019, "num_dag_node_jobs": 38286, "num_jobs_with_more_than_1_exec_att": 22255, "num_jobs_with_1+_holds": 35181, "num_jobs_over_rqst_disk": 16242, "num_short_jobs": 124705, "num_local_univ_jobs": 4075, "num_sched_univ_jobs": 16, "num_ckpt_able_jobs": 147975, "num_s'ty_jobs": 286454, "num_schedds": 13, "date": "2023-04-06", "query": "OSG-schedd-job-history", "report_period": "daily", "num_sites": 78, "num_projects": 35, "num_users": 47, "num_institutions": 49}