{"all_cpu_hours": 687021.6939, "num_uniq_job_ids": 698528, "pct_good_cpu_hours": 81.7745, "pct_ckpt_able": 2.568, "pct_rmed_jobs": 1.3935, "pct_short_jobs": 4.6169, "pct_jobs_with_more_than_1_exec_att": 2.6357, "pct_jobs_with_1+_holds": 4.8217, "pct_jobs_over_rqst_disk": 0.2374, "pct_jobs_using_s'ty": 88.1774, "total_files_xferd": 73630384, "osdf_files_xferd": 147665, "pct_osdf_files": 0.2005, "pct_osdf_bytes": 93.2371, "shadw_starts_per_job_id": 1.1928, "exec_atts_per_shadw_start": 0.8579, "holds_per_job_id": 0.1442, "mean_actv_hrs": 0.7938, "mean_setup_secs": 215.7872, "min_hrs": 0.0, "25pct_hrs": 0.0883, "med_hrs": 0.1503, "75pct_hrs": 0.265, "95pct_hrs": 5.0925, "max_hrs": 163.7761, "mean_hrs": 0.7971, "std_hrs": 1.7469, "input_files_per_exec_att": 100.899, "output_files_per_job": 2.986, "max_rqst_mem_mb": 43500, "med_used_mem_mb": 171.0, "max_used_mem_mb": 97657, "max_rqst_disk_gb": 157.2864, "max_used_disk_gb": 47.5, "max_rqst_cpus": 4, "good_cpu_hours": 561808.3847, "cpu_hours_per_bad_exec_att": 3.5944, "num_exec_atts": 714829, "num_shadw_starts": 833229, "num_job_holds": 100752, "num_rmed_jobs": 9734, "num_dag_node_jobs": 209667, "num_jobs_with_more_than_1_exec_att": 18411, "num_jobs_with_1+_holds": 33681, "num_jobs_over_rqst_disk": 1658, "num_short_jobs": 32250, "num_local_univ_jobs": 2232, "num_sched_univ_jobs": 144, "num_ckpt_able_jobs": 17938, "num_s'ty_jobs": 615944, "num_schedds": 13, "date": "2023-11-13", "query": "OSG-schedd-job-history", "report_period": "daily", "num_sites": 85, "num_projects": 29, "num_users": 45, "num_institutions": 53}