{"all_cpu_hours": 423443.5275, "num_uniq_job_ids": 390123, "pct_good_cpu_hours": 87.262, "pct_ckpt_able": 0.3089, "pct_rmed_jobs": 2.9703, "pct_short_jobs": 29.5158, "pct_jobs_with_more_than_1_exec_att": 5.5706, "pct_jobs_with_1+_holds": 2.2208, "pct_jobs_over_rqst_disk": 1.7025, "pct_jobs_using_s'ty": 20.694, "total_files_xferd": 11442478, "osdf_files_xferd": 21580, "pct_osdf_files": 0.1886, "pct_osdf_bytes": 29.1002, "shadw_starts_per_job_id": 1.1688, "exec_atts_per_shadw_start": 0.8848, "holds_per_job_id": 0.0692, "mean_actv_hrs": 0.9191, "mean_setup_secs": 47.1177, "min_hrs": 0.0, "25pct_hrs": 0.0319, "med_hrs": 0.0694, "75pct_hrs": 0.515, "95pct_hrs": 7.8328, "max_hrs": 128.8831, "mean_hrs": 1.3129, "std_hrs": 3.0326, "input_files_per_exec_att": 26.1374, "output_files_per_job": 2.5511, "max_rqst_mem_mb": 43500, "med_used_mem_mb": 10, "max_used_mem_mb": 122071, "max_rqst_disk_gb": 150.0, "max_used_disk_gb": 75.0, "max_rqst_cpus": 8, "good_cpu_hours": 369505.1297, "cpu_hours_per_bad_exec_att": 1.7486, "num_exec_atts": 403420, "num_shadw_starts": 455964, "num_job_holds": 27014, "num_rmed_jobs": 11588, "num_dag_node_jobs": 37637, "num_jobs_with_more_than_1_exec_att": 21732, "num_jobs_with_1+_holds": 8664, "num_jobs_over_rqst_disk": 6642, "num_short_jobs": 115148, "num_local_univ_jobs": 3299, "num_sched_univ_jobs": 188, "num_ckpt_able_jobs": 1205, "num_s'ty_jobs": 80732, "num_schedds": 11, "date": "2023-12-11", "query": "OSG-schedd-job-history", "report_period": "daily", "num_sites": 79, "num_projects": 28, "num_users": 37, "num_institutions": 50}