{"num_uniq_job_ids": 251195, "all_cpu_hours": 380036.7511, "pct_good_cpu_hours": 83.9815, "job_unit_hours": 688792.3311, "pct_ckpt_able": 0.4295, "pct_rmed_jobs": 1.467, "total_files_xferd": 1438303, "osdf_files_xferd": 45082, "pct_osdf_files": 3.1344, "pct_osdf_bytes": 78.7971, "shadw_starts_per_job_id": 1.1725, "exec_atts_per_shadw_start": 0.9289, "holds_per_job_id": 0.0661, "pct_short_jobs": 32.2916, "pct_jobs_with_more_than_1_exec_att": 8.446, "pct_jobs_with_1+_holds": 6.2804, "pct_jobs_over_rqst_disk": 9.0233, "pct_jobs_using_s'ty": 82.139, "mean_actv_hrs": 1.1022, "mean_setup_secs": 52.8953, "min_hrs": 0.0167, "25pct_hrs": 0.0517, "med_hrs": 0.3311, "75pct_hrs": 1.3244, "95pct_hrs": 9.1322, "max_hrs": 73.2656, "mean_hrs": 1.6139, "std_hrs": 3.7813, "input_files_per_exec_att": 3.2997, "output_files_per_job": 2.1601, "good_cpu_hours": 319160.5131, "cpu_hours_per_bad_exec_att": 2.0752, "num_exec_atts": 273580, "num_shadw_starts": 294524, "num_job_holds": 16600, "num_rmed_jobs": 3685, "num_dag_node_jobs": 3755, "num_jobs_with_more_than_1_exec_att": 21216, "num_jobs_with_1+_holds": 15776, "num_jobs_over_rqst_disk": 22666, "num_short_jobs": 81115, "num_local_univ_jobs": 14, "num_sched_univ_jobs": 52, "num_ckpt_able_jobs": 1079, "num_s'ty_jobs": 206329, "max_rqst_mem_mb": 40960, "med_used_mem_mb": 98.0, "max_used_mem_mb": 73243, "max_rqst_disk_gb": 41.943, "max_used_disk_gb": 15.0, "max_rqst_cpus": 4, "med_job_units": 1, "max_job_units": 10, "num_schedds": 11, "date": "2024-08-31", "query": "OSG-schedd-job-history", "report_period": "daily", "num_sites": 84, "num_projects": 27, "num_users": 31, "num_institutions": 56}