{"all_cpu_hours": 944370.7733, "num_uniq_job_ids": 431933, "pct_good_cpu_hours": 63.0651, "pct_ckpt_able": 8.3997, "pct_rmed_jobs": 7.0435, "pct_short_jobs": 21.8939, "pct_jobs_with_more_than_1_exec_att": 9.8913, "pct_jobs_with_1+_holds": 11.9229, "pct_jobs_over_rqst_disk": 3.3144, "pct_jobs_using_s'ty": 63.2385, "total_files_xferd": 4066585, "osdf_files_xferd": 116128, "pct_osdf_files": 2.8557, "pct_osdf_bytes": 33.3315, "shadw_starts_per_job_id": 1.9656, "exec_atts_per_shadw_start": 0.6041, "holds_per_job_id": 0.7525, "mean_actv_hrs": 1.4364, "mean_setup_secs": 121.1643, "min_hrs": 0.0167, "25pct_hrs": 0.1189, "med_hrs": 0.6303, "75pct_hrs": 2.3833, "95pct_hrs": 7.1139, "max_hrs": 62.3475, "mean_hrs": 1.8823, "std_hrs": 3.0806, "input_files_per_exec_att": 5.1547, "output_files_per_job": 3.4162, "max_rqst_mem_mb": 410000, "med_used_mem_mb": 464, "max_used_mem_mb": 463868, "max_rqst_disk_gb": 157.2864, "max_used_disk_gb": 125.0, "max_rqst_cpus": 64, "good_cpu_hours": 595568.7056, "cpu_hours_per_bad_exec_att": 2.8797, "num_exec_atts": 512875, "num_shadw_starts": 848995, "num_job_holds": 325016, "num_rmed_jobs": 30423, "num_dag_node_jobs": 57871, "num_jobs_with_more_than_1_exec_att": 42724, "num_jobs_with_1+_holds": 51499, "num_jobs_over_rqst_disk": 14316, "num_short_jobs": 94567, "num_local_univ_jobs": 1403, "num_sched_univ_jobs": 247, "num_ckpt_able_jobs": 36281, "num_s'ty_jobs": 273148, "num_schedds": 13, "date": "2024-03-13", "query": "OSG-schedd-job-history", "report_period": "daily", "num_sites": 75, "num_projects": 43, "num_users": 72, "num_institutions": 52}