{"all_cpu_hours": 908492.7064, "num_uniq_job_ids": 583901, "pct_good_cpu_hours": 84.0004, "pct_ckpt_able": 18.4029, "pct_rmed_jobs": 6.0687, "pct_short_jobs": 1.1067, "pct_jobs_with_more_than_1_exec_att": 4.8621, "pct_jobs_with_1+_holds": 11.642, "pct_jobs_over_rqst_disk": 13.8217, "pct_jobs_using_s'ty": 85.1057, "total_files_xferd": 7087994, "osdf_files_xferd": 208667, "pct_osdf_files": 2.944, "pct_osdf_bytes": 23.5449, "shadw_starts_per_job_id": 1.3233, "exec_atts_per_shadw_start": 0.7838, "holds_per_job_id": 0.273, "mean_actv_hrs": -1178821424365.2532, "mean_setup_secs": -8456458741864.23, "min_hrs": 0.0167, "25pct_hrs": 0.3031, "med_hrs": 0.6775, "75pct_hrs": 1.3925, "95pct_hrs": 5.0725, "max_hrs": 196.4669, "mean_hrs": 1.3367, "std_hrs": 2.0924, "input_files_per_exec_att": 8.5703, "output_files_per_job": 3.3558, "max_rqst_mem_mb": 204800, "med_used_mem_mb": 733, "max_used_mem_mb": 122071, "max_rqst_disk_gb": 157.2864, "max_used_disk_gb": 75.0, "max_rqst_cpus": 8, "good_cpu_hours": 763137.1431, "cpu_hours_per_bad_exec_att": 1.5833, "num_exec_atts": 605601, "num_shadw_starts": 772676, "num_job_holds": 159381, "num_rmed_jobs": 35435, "num_dag_node_jobs": 126268, "num_jobs_with_more_than_1_exec_att": 28390, "num_jobs_with_1+_holds": 67978, "num_jobs_over_rqst_disk": 80705, "num_short_jobs": 6462, "num_local_univ_jobs": 4321, "num_sched_univ_jobs": 22, "num_ckpt_able_jobs": 107455, "num_s'ty_jobs": 496933, "num_schedds": 14, "date": "2024-04-10", "query": "OSG-schedd-job-history", "report_period": "daily", "num_sites": 87, "num_projects": 44, "num_users": 72, "num_institutions": 57}