{"pct_shadw_with_o_start": 5.8537, "num_uniq_job_ids": 1228172, "all_cpu_hours": 850192.8497, "pct_good_cpu_hours": 73.6125, "job_unit_hours": 1387149.8311, "pct_ckpt_able": 5.0551, "pct_rmed_jobs": 2.5663, "total_files_xferd": 15217332, "osdf_files_xferd": 1158200, "pct_osdf_files": 7.6111, "pct_osdf_bytes": 84.2947, "shadw_starts_per_job_id": 1.0808, "exec_atts_per_shadw_start": 0.9415, "holds_per_job_id": 0.0322, "pct_short_jobs": 23.2808, "pct_jobs_with_more_than_1_exec_att": 2.5919, "pct_jobs_with_1+_holds": 2.1551, "pct_jobs_over_rqst_disk": 0.0463, "pct_jobs_using_s'ty": 80.7805, "mean_actv_hrs": -1208538602290.6567, "mean_setup_secs": -58861406224939.945, "min_hrs": 0.0167, "25pct_hrs": 0.0689, "med_hrs": 0.1567, "75pct_hrs": 0.4456, "95pct_hrs": 2.1156, "max_hrs": 885.4428, "mean_hrs": 0.5948, "std_hrs": 2.7395, "input_files_per_exec_att": 8.8183, "output_files_per_job": 3.4292, "good_cpu_hours": 625848.3194, "cpu_hours_per_bad_exec_att": 4.7249, "num_exec_atts": 1249674, "num_shadw_starts": 1327375, "num_job_holds": 39582, "num_rmed_jobs": 31519, "num_dag_node_jobs": 121952, "num_jobs_with_more_than_1_exec_att": 31833, "num_jobs_with_1+_holds": 26468, "num_jobs_over_rqst_disk": 569, "num_short_jobs": 285928, "num_ckpt_able_jobs": 62085, "num_s'ty_jobs": 992123, "max_rqst_mem_mb": 204800, "med_used_mem_mb": 74, "max_used_mem_mb": 97657, "max_rqst_disk_gb": 921.7484, "max_used_disk_gb": 100.0, "max_rqst_cpus": 32, "med_job_units": 1, "max_job_units": 220, "num_schedds": 17, "date": "2025-07-15", "query": "OSG-schedd-job-history", "report_period": "daily", "num_sites": 94, "num_projects": 49, "num_users": 79, "num_institutions": 81}