{"pct_shadw_with_o_start": 12.5018, "pct_shadw_input_fail": 8.416, "num_uniq_job_ids": 665634, "all_cpu_hours": 985817.0511, "pct_good_cpu_hours": 58.2989, "job_unit_hours": 1780119.7933, "pct_ckpt_able": 30.5937, "pct_rmed_jobs": 14.7704, "total_files_xferd": 7323099, "osdf_files_xferd": 335193, "pct_osdf_files": 4.5772, "pct_osdf_bytes": 30.9559, "shadw_starts_per_job_id": 1.1476, "exec_atts_per_shadw_start": 0.875, "holds_per_job_id": 0.2164, "pct_short_jobs": 4.2268, "pct_jobs_with_more_than_1_exec_att": 5.3226, "pct_jobs_with_1+_holds": 4.2091, "pct_jobs_over_rqst_disk": 0.3111, "pct_jobs_using_s'ty": 63.9958, "mean_actv_hrs": 1.2381, "mean_setup_secs": 90.2861, "input_files_per_exec_att": 8.1988, "output_files_per_job": 3.1067, "good_cpu_hours": 574720.0875, "cpu_hours_per_bad_exec_att": 3.4333, "num_job_holds": 144012, "num_rmed_jobs": 98317, "num_dag_node_jobs": 103437, "num_jobs_with_more_than_1_exec_att": 35429, "num_jobs_with_1+_holds": 28017, "num_jobs_over_rqst_disk": 2071, "num_short_jobs": 28135, "num_ckpt_able_jobs": 203642, "num_s'ty_jobs": 425978, "max_rqst_mem_mb": 256000, "med_used_mem_mb": 977, "max_used_mem_mb": 170899, "max_rqst_disk_gb": 209.7152, "max_used_disk_gb": 125.0, "max_rqst_cpus": 128, "med_job_units": 1.0, "max_job_units": 128, "num_job_starts": 668383, "num_shadow_starts": 763882, "num_shadow_starts_post_24.11.1": 720309, "num_transferinputerror": 60621, "num_jobs_post_24.11.1": 649186, "num_schedds": 17, "date": "2025-11-19", "query": "OSG-schedd-job-history", "report_period": "daily", "num_sites": 91, "num_projects": 46, "num_users": 75, "num_institutions": 81}