{"pct_shadw_with_o_start": 7.5235, "num_uniq_job_ids": 1741911, "all_cpu_hours": 875802.8297, "pct_good_cpu_hours": 77.2317, "job_unit_hours": 1404484.8422, "pct_ckpt_able": 2.1155, "pct_rmed_jobs": 5.5947, "total_files_xferd": 13853416, "osdf_files_xferd": 2156580, "pct_osdf_files": 15.5671, "pct_osdf_bytes": 89.6702, "shadw_starts_per_job_id": 1.073, "exec_atts_per_shadw_start": 0.9248, "holds_per_job_id": 0.0236, "pct_short_jobs": 5.0432, "pct_jobs_with_more_than_1_exec_att": 2.6617, "pct_jobs_with_1+_holds": 1.7667, "pct_jobs_over_rqst_disk": 19.4638, "pct_jobs_using_s'ty": 89.212, "mean_actv_hrs": 0.3604, "mean_setup_secs": 205.9744, "min_hrs": 0.0167, "25pct_hrs": 0.04, "med_hrs": 0.1108, "75pct_hrs": 0.375, "95pct_hrs": 1.2044, "max_hrs": 509.7258, "mean_hrs": 0.381, "std_hrs": 1.7365, "input_files_per_exec_att": 5.0464, "output_files_per_job": 3.0604, "good_cpu_hours": 676397.2164, "cpu_hours_per_bad_exec_att": 1.6491, "num_exec_atts": 1728403, "num_shadw_starts": 1869019, "num_job_holds": 41170, "num_rmed_jobs": 97454, "num_dag_node_jobs": 23254, "num_jobs_with_more_than_1_exec_att": 46365, "num_jobs_with_1+_holds": 30775, "num_jobs_over_rqst_disk": 339042, "num_short_jobs": 87848, "num_ckpt_able_jobs": 36850, "num_s'ty_jobs": 1553993, "max_rqst_mem_mb": 40960, "med_used_mem_mb": 98.0, "max_used_mem_mb": 73243, "max_rqst_disk_gb": 102.4, "max_used_disk_gb": 75.0, "max_rqst_cpus": 80, "med_job_units": 1, "max_job_units": 80, "num_schedds": 11, "date": "2025-08-04", "query": "OSG-schedd-job-history", "report_period": "daily", "num_sites": 93, "num_projects": 40, "num_users": 62, "num_institutions": 76}