{"pct_shadw_with_o_start": 5.4661, "num_uniq_job_ids": 2628231, "all_cpu_hours": 822568.5878, "pct_good_cpu_hours": 83.434, "job_unit_hours": 1531337.7069, "pct_ckpt_able": 0.8694, "pct_rmed_jobs": 2.338, "total_files_xferd": 22296218, "osdf_files_xferd": 4117630, "pct_osdf_files": 18.4678, "pct_osdf_bytes": 72.8353, "shadw_starts_per_job_id": 1.0522, "exec_atts_per_shadw_start": 0.9453, "holds_per_job_id": 0.0098, "pct_short_jobs": 30.2238, "pct_jobs_with_more_than_1_exec_att": 1.2096, "pct_jobs_with_1+_holds": 0.591, "pct_jobs_over_rqst_disk": 0.5819, "pct_jobs_using_s'ty": 39.251, "mean_actv_hrs": 0.2301, "mean_setup_secs": 28.5932, "min_hrs": -0.005, "25pct_hrs": 0.0486, "med_hrs": 0.0864, "75pct_hrs": 0.1761, "95pct_hrs": 1.3089, "max_hrs": 820.4919, "mean_hrs": 0.3426, "std_hrs": 2.0749, "input_files_per_exec_att": 6.8481, "output_files_per_job": 1.7019, "good_cpu_hours": 686302.2689, "cpu_hours_per_bad_exec_att": 2.8141, "num_exec_atts": 2614231, "num_shadw_starts": 2765390, "num_job_holds": 25800, "num_rmed_jobs": 61448, "num_dag_node_jobs": 372323, "num_jobs_with_more_than_1_exec_att": 31790, "num_jobs_with_1+_holds": 15534, "num_jobs_over_rqst_disk": 15293, "num_short_jobs": 794352, "num_ckpt_able_jobs": 22849, "num_s'ty_jobs": 1031606, "max_rqst_mem_mb": 131072, "med_used_mem_mb": 74, "max_used_mem_mb": 97657, "max_rqst_disk_gb": 262.144, "max_used_disk_gb": 200.0, "max_rqst_cpus": 64, "med_job_units": 1, "max_job_units": 64, "num_schedds": 13, "date": "2025-06-12", "query": "OSG-schedd-job-history", "report_period": "daily", "num_sites": 95, "num_projects": 47, "num_users": 86, "num_institutions": 79}