{"pct_shadw_with_o_start": 16.9172, "pct_shadw_input_fail": 0.1738, "num_uniq_job_ids": 903019, "all_cpu_hours": 1018337.0475, "pct_good_cpu_hours": 71.513, "job_unit_hours": 1852104.9872, "pct_ckpt_able": 5.6828, "pct_rmed_jobs": 2.2507, "total_files_xferd": 8510643, "osdf_files_xferd": 234246, "pct_osdf_files": 2.7524, "pct_osdf_bytes": 30.7789, "shadw_starts_per_job_id": 1.2735, "exec_atts_per_shadw_start": 0.8308, "holds_per_job_id": 0.0786, "pct_short_jobs": 1.5147, "pct_jobs_with_more_than_1_exec_att": 5.1465, "pct_jobs_with_1+_holds": 4.9483, "pct_jobs_over_rqst_disk": 0.0657, "pct_jobs_using_s'ty": 22.4917, "mean_actv_hrs": 0.9337, "mean_setup_secs": 46.7669, "mean_strip_secs": 31.457, "input_files_per_exec_att": 5.2194, "output_files_per_job": 3.9151, "good_cpu_hours": 728243.1733, "cpu_hours_per_bad_exec_att": 2.8095, "num_job_holds": 70977, "num_rmed_jobs": 20324, "num_dag_node_jobs": 106906, "num_jobs_with_more_than_1_exec_att": 46474, "num_jobs_with_1+_holds": 44684, "num_jobs_over_rqst_disk": 593, "num_short_jobs": 13678, "num_ckpt_able_jobs": 51317, "num_s'ty_jobs": 203104, "max_rqst_mem_mb": 90000, "med_used_mem_mb": 977.0, "max_used_mem_mb": 97657, "max_rqst_disk_gb": 62.9146, "max_used_disk_gb": 75.0, "max_rqst_cpus": 256, "med_job_units": 1.0, "max_job_units": 256, "num_job_starts": 955431, "num_shadow_starts": 1149975, "num_shadow_starts_post_24.11.1": 1148519, "num_transferinputerror": 1996, "num_jobs_post_24.11.1": 902224, "num_schedds": 14, "date": "2025-11-27", "query": "OSG-schedd-job-history", "report_period": "daily", "num_sites": 91, "num_projects": 37, "num_users": 59, "num_institutions": 85}