{"pct_shadw_with_o_start": 96.5562, "pct_shadw_input_fail": 0.0081, "num_uniq_job_ids": 667383, "all_cpu_hours": 921283.0411, "pct_good_cpu_hours": 61.1033, "job_unit_hours": 1364954.5044, "pct_ckpt_able": 2.0795, "pct_rmed_jobs": 4.3101, "total_files_xferd": 41824401, "osdf_files_xferd": 915669, "pct_osdf_files": 2.1893, "pct_osdf_bytes": 87.8673, "shadw_starts_per_job_id": 29.877, "exec_atts_per_shadw_start": 0.0344, "holds_per_job_id": 58.632, "pct_short_jobs": 26.8408, "pct_jobs_with_more_than_1_exec_att": 3.6059, "pct_jobs_with_1+_holds": 1.86, "pct_jobs_over_rqst_disk": 0.3055, "pct_jobs_using_s'ty": 58.8737, "mean_actv_hrs": 0.8944, "mean_setup_secs": 20.791, "mean_strip_secs": 0.9422, "input_files_per_exec_att": 57.4382, "output_files_per_job": 3.6573, "good_cpu_hours": 562934.0575, "cpu_hours_per_bad_exec_att": 7.718, "num_job_holds": 39130028, "num_rmed_jobs": 28765, "num_dag_node_jobs": 108852, "num_jobs_with_more_than_1_exec_att": 24065, "num_jobs_with_1+_holds": 12413, "num_jobs_over_rqst_disk": 2039, "num_short_jobs": 179131, "num_ckpt_able_jobs": 13878, "num_s'ty_jobs": 392913, "max_rqst_mem_mb": 8388608, "med_used_mem_mb": 74.0, "max_used_mem_mb": 97657, "max_rqst_disk_gb": 512.0, "max_used_disk_gb": 45.0, "max_rqst_cpus": 16, "med_job_units": 1.0, "max_job_units": 123, "pct_shadw_with_o_start_csv": 96.5562, "pct_shadw_input_fail_csv": 0.0081, "num_job_starts": 686668, "num_shadow_starts": 19939414, "num_shadows_with_o_start": 19252746, "pct_of_all_shadow_fails": 100.0, "num_shadow_starts_post_24.11.1": 19936870, "num_transferinputerror": 1613, "num_jobs_post_24.11.1": 666402, "num_schedds": 18, "date": "2026-07-14", "query": "OSG-schedd-job-history", "report_period": "daily", "num_sites": 76, "num_projects": 64, "num_users": 158, "num_institutions": 80}