{"pct_shadw_with_o_start": 5.3814, "pct_shadw_input_fail": 0.4307, "num_uniq_job_ids": 876134, "all_cpu_hours": 1164524.7044, "pct_good_cpu_hours": 81.5342, "job_unit_hours": 2081673.8772, "pct_ckpt_able": 2.6263, "pct_rmed_jobs": 5.7293, "total_files_xferd": 56590427, "osdf_files_xferd": 926260, "pct_osdf_files": 1.6368, "pct_osdf_bytes": 81.7781, "shadw_starts_per_job_id": 1.0637, "exec_atts_per_shadw_start": 0.9462, "holds_per_job_id": 0.0361, "pct_short_jobs": 11.7851, "pct_jobs_with_more_than_1_exec_att": 3.5233, "pct_jobs_with_1+_holds": 1.8415, "pct_jobs_over_rqst_disk": 0.1009, "pct_jobs_using_s'ty": 63.2992, "mean_actv_hrs": 1.0217, "mean_setup_secs": 34.5076, "mean_strip_secs": 3.4009, "input_files_per_exec_att": 60.0951, "output_files_per_job": 4.2509, "good_cpu_hours": 949485.7261, "cpu_hours_per_bad_exec_att": 4.333, "num_job_holds": 31664, "num_rmed_jobs": 50196, "num_dag_node_jobs": 283129, "num_jobs_with_more_than_1_exec_att": 30869, "num_jobs_with_1+_holds": 16134, "num_jobs_over_rqst_disk": 884, "num_short_jobs": 103253, "num_ckpt_able_jobs": 23010, "num_s'ty_jobs": 554586, "max_rqst_mem_mb": 366213, "med_used_mem_mb": 416.0, "max_used_mem_mb": 122071, "max_rqst_disk_gb": 157.2864, "max_used_disk_gb": 175.0, "max_rqst_cpus": 32, "med_job_units": 1, "max_job_units": 90, "pct_shadw_with_o_start_csv": 5.3814, "pct_shadw_input_fail_csv": 0.4307, "num_job_starts": 881818, "num_shadow_starts": 931971, "num_shadows_with_o_start": 50153, "pct_of_all_shadow_fails": 100.0, "num_shadow_starts_post_24.11.1": 930753, "num_transferinputerror": 4009, "num_jobs_post_24.11.1": 875975, "num_schedds": 14, "date": "2026-04-12", "query": "OSG-schedd-job-history", "report_period": "daily", "num_sites": 99, "num_projects": 47, "num_users": 65, "num_institutions": 87}