{"pct_shadw_with_o_start": 3.2817, "pct_shadw_input_fail": 0.1187, "num_uniq_job_ids": 1326456, "all_cpu_hours": 1018280.87, "pct_good_cpu_hours": 65.7937, "job_unit_hours": 1316212.3258, "pct_ckpt_able": 0.2695, "pct_rmed_jobs": 2.2841, "total_files_xferd": 12410901, "osdf_files_xferd": 3033982, "pct_osdf_files": 24.4461, "pct_osdf_bytes": 68.6076, "shadw_starts_per_job_id": 1.0497, "exec_atts_per_shadw_start": 0.9672, "holds_per_job_id": 0.0475, "pct_short_jobs": 7.2917, "pct_jobs_with_more_than_1_exec_att": 2.2479, "pct_jobs_with_1+_holds": 0.522, "pct_jobs_over_rqst_disk": 0.0777, "pct_jobs_using_s'ty": 67.3284, "mean_actv_hrs": 0.4398, "mean_setup_secs": 14.6552, "mean_strip_secs": 0.6996, "input_files_per_exec_att": 4.1144, "output_files_per_job": 5.2803, "good_cpu_hours": 669964.7142, "cpu_hours_per_bad_exec_att": 7.1679, "num_job_holds": 63003, "num_rmed_jobs": 30298, "num_dag_node_jobs": 114329, "num_jobs_with_more_than_1_exec_att": 29818, "num_jobs_with_1+_holds": 6924, "num_jobs_over_rqst_disk": 1030, "num_short_jobs": 96721, "num_ckpt_able_jobs": 3575, "num_s'ty_jobs": 893081, "max_rqst_mem_mb": 262144, "med_used_mem_mb": 245.0, "max_used_mem_mb": 195313, "max_rqst_disk_gb": 272.6298, "max_used_disk_gb": 45.0, "max_rqst_cpus": 16, "med_job_units": 1.0, "max_job_units": 65, "pct_shadw_with_o_start_csv": 3.2817, "pct_shadw_input_fail_csv": 0.1187, "num_job_starts": 1346709, "num_shadow_starts": 1392404, "num_shadows_with_o_start": 45695, "pct_of_all_shadow_fails": 100.0, "num_shadow_starts_post_24.11.1": 1392360, "num_transferinputerror": 1653, "num_jobs_post_24.11.1": 1326412, "num_schedds": 16, "date": "2026-07-07", "query": "OSG-schedd-job-history", "report_period": "daily", "num_sites": 83, "num_projects": 60, "num_users": 109, "num_institutions": 86}