{"pct_shadw_with_o_start": 1.8907, "pct_shadw_input_fail": 0.1291, "num_uniq_job_ids": 922408, "all_cpu_hours": 805923.2881, "pct_good_cpu_hours": 75.7535, "job_unit_hours": 1252589.0022, "pct_ckpt_able": 1.5709, "pct_rmed_jobs": 6.7796, "total_files_xferd": 8936360, "osdf_files_xferd": 1810155, "pct_osdf_files": 20.2561, "pct_osdf_bytes": 91.0406, "shadw_starts_per_job_id": 1.0329, "exec_atts_per_shadw_start": 0.9811, "holds_per_job_id": 0.0455, "pct_short_jobs": 23.3119, "pct_jobs_with_more_than_1_exec_att": 3.7975, "pct_jobs_with_1+_holds": 0.8813, "pct_jobs_over_rqst_disk": 7.2859, "pct_jobs_using_s'ty": 78.0752, "mean_actv_hrs": 0.6272, "mean_setup_secs": 16.8682, "mean_strip_secs": 1.7932, "input_files_per_exec_att": 4.7816, "output_files_per_job": 5.1336, "good_cpu_hours": 610514.8164, "cpu_hours_per_bad_exec_att": 2.6001, "num_job_holds": 41971, "num_rmed_jobs": 62536, "num_dag_node_jobs": 96322, "num_jobs_with_more_than_1_exec_att": 35028, "num_jobs_with_1+_holds": 8129, "num_jobs_over_rqst_disk": 67206, "num_short_jobs": 215031, "num_ckpt_able_jobs": 14490, "num_s'ty_jobs": 720172, "max_rqst_mem_mb": 131072, "med_used_mem_mb": 123, "max_used_mem_mb": 122071, "max_rqst_disk_gb": 81.92, "max_used_disk_gb": 50.0, "max_rqst_cpus": 16, "med_job_units": 1.0, "max_job_units": 32, "pct_shadw_with_o_start_csv": 1.8907, "pct_shadw_input_fail_csv": 0.1291, "num_job_starts": 934769, "num_shadow_starts": 952783, "num_shadows_with_o_start": 18014, "pct_of_all_shadow_fails": 100.0, "num_shadow_starts_post_24.11.1": 952659, "num_transferinputerror": 1230, "num_jobs_post_24.11.1": 922286, "num_schedds": 14, "date": "2026-06-15", "query": "OSG-schedd-job-history", "report_period": "daily", "num_sites": 82, "num_projects": 60, "num_users": 100, "num_institutions": 84}