{"pct_shadw_with_o_start": 6.7259, "pct_shadw_input_fail": 4.646, "num_uniq_job_ids": 490062, "all_cpu_hours": 840035.7558, "pct_good_cpu_hours": 74.582, "job_unit_hours": 1151410.7342, "pct_ckpt_able": 4.0423, "pct_rmed_jobs": 8.7083, "total_files_xferd": 3386947, "osdf_files_xferd": 443025, "pct_osdf_files": 13.0804, "pct_osdf_bytes": 90.382, "shadw_starts_per_job_id": 1.0672, "exec_atts_per_shadw_start": 0.9327, "holds_per_job_id": 0.0872, "pct_short_jobs": 27.7402, "pct_jobs_with_more_than_1_exec_att": 3.9305, "pct_jobs_with_1+_holds": 2.8184, "pct_jobs_over_rqst_disk": 0.2483, "pct_jobs_using_s'ty": 55.9499, "mean_actv_hrs": 1.2628, "mean_setup_secs": 23.8995, "mean_strip_secs": 0.7774, "input_files_per_exec_att": 4.0816, "output_files_per_job": 3.0231, "good_cpu_hours": 626515.855, "cpu_hours_per_bad_exec_att": 6.6703, "num_job_holds": 42729, "num_rmed_jobs": 42676, "num_dag_node_jobs": 34975, "num_jobs_with_more_than_1_exec_att": 19262, "num_jobs_with_1+_holds": 13812, "num_jobs_over_rqst_disk": 1217, "num_short_jobs": 135944, "num_ckpt_able_jobs": 19810, "num_s'ty_jobs": 274189, "max_rqst_mem_mb": 8388608, "med_used_mem_mb": 74.0, "max_used_mem_mb": 219727, "max_rqst_disk_gb": 90.1775, "max_used_disk_gb": 45.0, "max_rqst_cpus": 16, "med_job_units": 1.0, "max_job_units": 64, "pct_shadw_with_o_start_csv": 6.7259, "pct_shadw_input_fail_csv": 4.646, "num_job_starts": 487801, "num_shadow_starts": 522976, "num_shadows_with_o_start": 35175, "pct_of_all_shadow_fails": 100.0, "num_shadow_starts_post_24.11.1": 522925, "num_transferinputerror": 24295, "num_jobs_post_24.11.1": 490011, "num_schedds": 17, "date": "2026-07-13", "query": "OSG-schedd-job-history", "report_period": "daily", "num_sites": 74, "num_projects": 65, "num_users": 157, "num_institutions": 80}